[{"country":"DZ","c99":"Aucune disposition soulign\u00e9e dans ce sens","c1":"0","c0":"Algeria"},{"country":"BR","c99":"Law No. 10.406 of 10 January 2002 \u2013  Civil Code, Article 1.790","c1":"3","c0":"Brazil"},{"country":"KH","c99":"No provision could be located","c1":"0","c0":"Cambodia"},{"country":"CL","c99":"Falta de disposici\u00f3n","c1":"0","c0":"Chile"},{"country":"CN","c99":"No provision could be located","c1":"0","c0":"China"},{"country":"CO","c99":"Ley 979\/05","c1":"3","c0":"Colombia"},{"country":"EC","c99":"Constituci\u00f3n Pol\u00edtica del Ecuador, 2008, Art\u00edculo 68 *** C\u00f3digo Civil, LIBRO I, Art\u00edculo 222","c1":"4","c0":"Ecuador"},{"country":"ET","c99":"Revised Family Code, 2000, Article 102","c1":"3","c0":"Ethiopia"},{"country":"GH","c99":"The Property Rights of Spouses Bill, 2009, Sections 3 and 23","c1":"2","c0":"Ghana"},{"country":"GT","c99":"C\u00f3digo Civil,  Art\u00edculo 182","c1":"3","c0":"Guatemala"},{"country":"KE","c99":"No provision could be located","c1":"0","c0":"Kenya"},{"country":"MG","c99":"Aucune disposition relev\u00e9e","c1":"0","c0":"Madagascar"},{"country":"ML","c99":"Aucune disposition relev\u00e9e","c1":"0","c0":"Mali"},{"country":"MX","c99":"Falta de disposici\u00f3n","c1":"0","c0":"Mexico"},{"country":"MN","c99":"No provision could be located","c1":"0","c0":"Mongolia"},{"country":"MA","c99":"Aucune disposition relev\u00e9e","c1":"0","c0":"Morocco"},{"country":"NP","c99":"No provision could be located","c1":"0","c0":"Nepal"},{"country":"NI","c99":"C\u00f3digo de Familia,  Ley 870, 2014,  Art\u00edculos 90 y 106","c1":"3","c0":"Nicaragua"},{"country":"PA","c99":"Falta de disposici\u00f3n","c1":"0","c0":"Panama"},{"country":"PE","c99":"C\u00f3digo civil - Decreto Legislativo No. 295, Art\u00edculo 326","c1":"3","c0":"Peru"},{"country":"RW","c99":"Draft Law governing persons and family, Article 159","c1":"2","c0":"Rwanda"},{"country":"SL","c99":"No provision could be located","c1":"0","c0":"Sierra Leone"},{"country":"ZA","c99":"No provision could be located","c1":"0","c0":"South Africa"},{"country":"TN","c99":"Aucune disposition relev\u00e9e","c1":"0","c0":"Tunisia"},{"country":"UY","c99":"Ley No. 18.246 - Uni\u00f3n concubinaria, Art\u00edculo 5","c1":"3","c0":"Uruguay"}]